hebi/__init__.py
hebi/__main__.py
hebi/compiler.py
hebi/prelude.py
hebi/type_inference.py
hebi/typed_ast.py
hebi/util.py
hebi/optimize/__init__.py
hebi/optimize/optimize_remove_deadvars.py
hebi/optimize/optimize_remove_pass.py
hebi/optimize/optimize_varlen.py
hebi/rewrite/__init__.py
hebi/rewrite/rewrite_augassign.py
hebi/rewrite/rewrite_forbidden_overwrites.py
hebi/rewrite/rewrite_import.py
hebi/rewrite/rewrite_import_dataclasses.py
hebi/rewrite/rewrite_import_hashlib.py
hebi/rewrite/rewrite_import_plutusdata.py
hebi/rewrite/rewrite_import_typing.py
hebi/rewrite/rewrite_inject_builtin_constr.py
hebi/rewrite/rewrite_inject_builtins.py
hebi/rewrite/rewrite_remove_type_stuff.py
hebi/rewrite/rewrite_tuple_assign.py
hebi/tests/__init__.py
hebi/tests/test_builtins.py
hebi/tests/test_misc.py
hebi/tests/test_ops.py
hebi/tests/test_stdlib.py
hebi-0.9.2.dist-info/LICENSE.txt
hebi-0.9.2.dist-info/METADATA
hebi-0.9.2.dist-info/WHEEL
hebi-0.9.2.dist-info/entry_points.txt
hebi-0.9.2.dist-info/top_level.txt
hebi-0.9.2.dist-info/RECORD
