Metadata-Version: 2.1
Name: hebi
Version: 0.9.2
Summary: A simple pythonic programming language for Smart Contracts on Cardano 
Home-page: https://github.com/imperatorlang/hebi
Author: nielstron
Author-email: n.muendler@web.de
License: MIT
Keywords: python cardano smart contract blockchain verification haskell
Classifier: Development Status :: 3 - Alpha
Classifier: Intended Audience :: Developers
Classifier: Topic :: Software Development :: Compilers
Classifier: License :: OSI Approved :: MIT License
Classifier: Programming Language :: Python :: 3.8
Requires-Python: >=3.8, <3.9
License-File: LICENSE.txt
Requires-Dist: uplc (==0.5.6)
Requires-Dist: pluthon (==0.2.15)
Requires-Dist: pycardano (==0.7.2)
Requires-Dist: frozenlist (==1.3.3)
Requires-Dist: pyaiken (==0.4.0)
